tingg/__init__.py
tingg/checkout.py
tingg/constants.py
tingg/encryption.py
tingg/express.py
tingg/validation.py
Tingg-0.1.6.dist-info/LICENSE.rst
Tingg-0.1.6.dist-info/METADATA
Tingg-0.1.6.dist-info/WHEEL
Tingg-0.1.6.dist-info/top_level.txt
Tingg-0.1.6.dist-info/RECORD
