Metadata-Version: 2.1
Name: Tingg
Version: 0.1.6
Summary: A simple package to help you streamline your integration to Tingg  APIs.
Maintainer-email: Cellulant <platforms@cellulant.io>, Howard Mnengwa <howard@mnengwa.com>, Muracia Ndungu <muracia.ndungu@cellulant.io>
License: GNU GENERAL PUBLIC LICENSE
Project-URL: Documentation, https://docs.tingg.africa/docs/checkout-v3-sdks-ui-library
Project-URL: Changes, https://gitlab.com/cellulant-public/tingg-global-merchants/sdks/python-sdk/-/milestones
Project-URL: Source Code, https://gitlab.com/cellulant-public/tingg-global-merchants/sdks/python-sdk
Project-URL: Issue Tracker, https://gitlab.com/cellulant-public/tingg-global-merchants/sdks/python-sdk/-/issues
Project-URL: Chat, https://docs.tingg.africa/discuss
Classifier: Environment :: Web Environment
Classifier: Intended Audience :: Developers
Classifier: License :: OSI Approved :: GNU General Public License (GPL)
Classifier: Operating System :: OS Independent
Classifier: Programming Language :: Python
Requires-Python: >=3.6
License-File: LICENSE.rst
Requires-Dist: requests
Requires-Dist: pycryptodome
